dollar_value_example/__init__.py
dollar_value_example-0.0.1.dist-info/LICENSE
dollar_value_example-0.0.1.dist-info/METADATA
dollar_value_example-0.0.1.dist-info/WHEEL
dollar_value_example-0.0.1.dist-info/top_level.txt
dollar_value_example-0.0.1.dist-info/RECORD
