Metadata-Version: 2.1
Name: dollar-value-example
Version: 0.0.1
Summary: Application for dollar value
Author: Atmostone
License: UNKNOWN
Platform: UNKNOWN
Classifier: Programming Language :: Python :: 3
Classifier: License :: OSI Approved :: MIT License
Classifier: Operating System :: OS Independent
Requires-Python: >=3.6
License-File: LICENSE
Requires-Dist: requests
